gen_latex/__init__.py
gen_latex/cli.py
gen_latex/latex.py
gen_latex_petr1furious-0.1.1.dist-info/METADATA
gen_latex_petr1furious-0.1.1.dist-info/WHEEL
gen_latex_petr1furious-0.1.1.dist-info/entry_points.txt
gen_latex_petr1furious-0.1.1.dist-info/RECORD
