Metadata-Version: 2.4
Name: gen-latex-petr1furious
Version: 0.1.1
Requires-Python: >=3.14
Requires-Dist: typer>=0.20.0
